certbot_dns_glesys.py
certbot_dns_glesys-2.1.0.dist-info/LICENSE
certbot_dns_glesys-2.1.0.dist-info/METADATA
certbot_dns_glesys-2.1.0.dist-info/WHEEL
certbot_dns_glesys-2.1.0.dist-info/entry_points.txt
certbot_dns_glesys-2.1.0.dist-info/top_level.txt
certbot_dns_glesys-2.1.0.dist-info/RECORD
