Metadata-Version: 2.1
Name: certbot-dns-glesys
Version: 2.1.0
Summary: GleSYS DNS authentication plugin for Certbot
Home-page: https://www.github.com/runfalk/certbot-dns-glesys
Author: Andreas Runfalk
Author-email: andreas@runfalk.se
License: BSD
Platform: UNKNOWN
Classifier: Development Status :: 5 - Production/Stable
Classifier: Environment :: Plugins
Classifier: Intended Audience :: Developers
Classifier: License :: OSI Approved :: BSD License
Classifier: Programming Language :: Python
Classifier: Programming Language :: Python :: 3.6
Classifier: Programming Language :: Python :: 3.7
Classifier: Programming Language :: Python :: 3.8
Classifier: Programming Language :: Python :: 3.9
Classifier: Topic :: Internet :: Name Service (DNS)
Classifier: Topic :: System :: Systems Administration
Classifier: Topic :: Utilities
License-File: LICENSE
Requires-Dist: acme (>=1.8.0)
Requires-Dist: certbot (>=1.7.0)
Requires-Dist: requests
Provides-Extra: dev
Requires-Dist: pytest ; extra == 'dev'
Requires-Dist: wheel ; extra == 'dev'
